{
  "A": {
    "tput": [
      30181.4,
      34846.0,
      49335.7,
      72119.5,
      79050.7,
      86816.5,
      78700.0,
      90204.2,
      109359.0,
      103412.0
    ],
    "tnum": [
      1,
      2,
      3,
      4,
      5,
      6,
      7,
      8,
      9,
      10
    ]
  },
  "B": {
    "tput": [
      11214.2,
      11987.6,
      12214.1,
      13809.8,
      12677.6,
      14767.6,
      17100.8,
      19833.0,
      21491.2,
      19503.8
    ],
    "tnum": [
      1,
      2,
      3,
      4,
      5,
      6,
      7,
      8,
      9,
      10
    ]
  },
  "C": {
    "tput": [
      9204.26,
      10040.0,
      9982.23,
      10324.6,
      11029.9,
      16236.7,
      15684.6,
      17293.9,
      21966.7,
      17190.3
    ],
    "tnum": [
      1,
      2,
      3,
      4,
      5,
      6,
      7,
      8,
      9,
      10
    ]
  },
  "D": {
    "tput": [
      12243.3,
      12622.2,
      13119.6,
      14807.0,
      15118.4,
      20654.1,
      22260.5,
      21702.7,
      27996.3,
      22892.7
    ],
    "tnum": [
      1,
      2,
      3,
      4,
      5,
      6,
      7,
      8,
      9,
      10
    ]
  },
  "E": {
    "tput": [
      32910.4,
      39377.6,
      50524.2,
      67325.6,
      79579.4,
      90057.2,
      97872.7,
      104692.0,
      92696.6,
      85001.3
    ],
    "tnum": [
      1,
      2,
      3,
      4,
      5,
      6,
      7,
      8,
      9,
      10
    ]
  }
}